Computer Architecture/lab 2/adder1B.v
module adder1B (
    input A,
    input B,
    input Cin,
    output S,
    output Cout
);


    assign S = A ^ B ^ Cin;
    assign Cout = (A & B) | (A ^ B) &  Cin;  

endmodule

Computer Architecture/lab 2/adder1B_tb.v
`timescale 1ns/1ps
module adder1B_tb;

    // Inputs
    reg A;
    reg B;
    reg Cin;

    // Outputs
    wire S;
    wire Cout;

    // Instantiate the Unit Under Test (UUT)
    adder1B uut (A, B, Cin, S, Cout);

    initial begin

        $dumpfile("Adder1B_tb_test.vcd");
        $dumpvars(0, adder1B_tb);


        // Initialize Inputs
        A = 1'b0;
        B = 1'b0;
        Cin = 1'b0;

        #20
        A = 1'b0;
        B = 1'b0;
        Cin = 1'b1;

        #20
        A = 1'b0;
        B = 1'b1;
        Cin = 1'b0;

        #20
        A = 1'b0;
        B = 1'b1;
        Cin = 1'b1;

        #20
        A = 1'b1;
        B = 1'b0;
        Cin = 1'b0;

        #20
        A = 1'b1;
        B = 1'b0;
        Cin = 1'b1;

        #20
        A = 1'b1;
        B = 1'b1;
        Cin = 1'b0;

        #20
        A = 1'b1;
        B = 1'b1;
        Cin = 1'b1;

        #20
        $finish;
    end

    initial begin
        $monitor("A=%b,B=%b,Cin=%b,S=%b,Cout=%b\n", A, B, Cin, S, Cout);
    end

endmodule

Computer Architecture/lab 2/Adder1B_tb_test.vcd
$date
	Sat May 04 12:08:20 2024
$end
$version
	Icarus Verilog
$end
$timescale
	1ps
$end
$scope module adder1B_tb $end
$var wire 1 ! S $end
$var wire 1 " Cout $end
$var reg 1 # A $end
$var reg 1 $ B $end
$var reg 1 % Cin $end
$scope module uut $end
$var wire 1 # A $end
$var wire 1 $ B $end
$var wire 1 % Cin $end
$var wire 1 " Cout $end
$var wire 1 ! S $end
$upscope $end
$upscope $end
$enddefinitions $end
#0
$dumpvars
0%
0$
0#
0"
0!
$end
#20000
1!
1%
#40000
0%
1$
#60000
1"
0!
1%
#80000
0"
1!
0%
0$
1#
#100000
1"
0!
1%
#120000
0%
1$
#140000
1!
1%
